{
  "configuration": {
    "version": 2,
    "url": "https://res.cloudinary.com/saas-ag/raw/upload/schemata2/viu/configuration_v2.json",
    "entity": "PRODUCT",
    "hash": "64d96e408d28f234"
  },
  "favoriteProducts": {
    "version": 2,
    "url": "https://res.cloudinary.com/saas-ag/raw/upload/schemata2/viu/favoriteProducts_v2.json",
    "entity": "CUSTOMER",
    "hash": "b5edbd90c9a00234"
  },
  "information": {
    "version": 2,
    "url": "https://res.cloudinary.com/saas-ag/raw/upload/schemata2/viu/information_v2.json",
    "entity": "EMPLOYEE",
    "hash": "cef74f682602979e"
  },
  "68e27d7a68ce91215abc0f23": {
    "version": 1,
    "url": "https://res.cloudinary.com/saas-ag/raw/upload/schemata2/viu/68e27d7a68ce91215abc0f23_v1.json",
    "entity": "UNKNOWN",
    "hash": "6faf189cb3da0e64"
  },
  "68e35f6668ce91215abc0f24": {
    "version": 3,
    "url": "https://res.cloudinary.com/saas-ag/raw/upload/schemata2/viu/68e35f6668ce91215abc0f24_v3.json",
    "entity": "UNKNOWN",
    "hash": "1e277a081e0c6d96"
  },
  "693be2a38a93a7474c256771": {
    "version": 2,
    "url": "https://res.cloudinary.com/saas-ag/raw/upload/schemata2/viu/693be2a38a93a7474c256771_v2.json",
    "entity": "UNKNOWN",
    "hash": "cef74f682602979e"
  },
  "69f39b546091ad27d6bf29a1": {
    "version": 1,
    "url": "https://res.cloudinary.com/saas-ag/raw/upload/schemata2/viu/69f39b546091ad27d6bf29a1_v1.json",
    "entity": "PRODUCT",
    "hash": "dc3f22605d3c51b4"
  }
}